{
  "experiment": "t16_training_matched_direct_operator_v3a",
  "scientific_status": "DEVELOPMENT_PILOT_PARTIAL_NEURAL_GATES",
  "development_fields_only": true,
  "training_mask_matches_evaluation": true,
  "source_field_count": 256,
  "independent_test_field_count": 96,
  "model_seed_count": 3,
  "reconstruction_budgets": [
    4,
    6,
    8
  ],
  "installed_camera_count": {
    "4": 5,
    "6": 7,
    "8": 9
  },
  "fixed_query_index": 4,
  "audit_query_index": 3,
  "classical_champions": {
    "4": "ridge",
    "6": "ridge",
    "8": "ridge"
  },
  "selected_ridge_relative": {
    "4": 1e-06,
    "6": 1e-06,
    "8": 1e-05
  },
  "labels": {
    "physics_lift": "train-calibrated physics lift",
    "ridge": "validation-tuned ridge",
    "unet": "FBP-lift residual 3D U-Net",
    "fno": "FBP-lift residual 3D FNO",
    "ridge_unet": "ridge-initialized residual 3D U-Net",
    "ridge_fno": "ridge-initialized residual 3D FNO"
  },
  "summary": [
    {
      "total_budget": 4,
      "method": "fno",
      "independent_field_count": 96,
      "model_seed_count": 3,
      "source_domain_count": 4,
      "classical_champion": "ridge",
      "mean_field_rel_l2": 0.5864014649349782,
      "mean_audit_reprojection_rel_l2": 0.633525143791404,
      "mean_improvement_vs_classical_pct": -2.157901422751405,
      "median_improvement_vs_classical_pct": -11.030528259154316,
      "p10_improvement_vs_classical_pct": -17.98324734056034,
      "harm_rate_gt_1pct_vs_classical": 0.65625,
      "improvement_ci95_cluster_low": -5.1166645223296765,
      "improvement_ci95_cluster_high": 0.8842379337704652
    },
    {
      "total_budget": 4,
      "method": "physics_lift",
      "independent_field_count": 96,
      "model_seed_count": 3,
      "source_domain_count": 4,
      "classical_champion": "ridge",
      "mean_field_rel_l2": 0.7460483262936274,
      "mean_audit_reprojection_rel_l2": 0.7670113540564973,
      "mean_improvement_vs_classical_pct": -38.11048194110135,
      "median_improvement_vs_classical_pct": -29.130736971239386,
      "p10_improvement_vs_classical_pct": -74.65310711293608,
      "harm_rate_gt_1pct_vs_classical": 1.0,
      "improvement_ci95_cluster_low": -41.18890932951521,
      "improvement_ci95_cluster_high": -35.167707819830795
    },
    {
      "total_budget": 4,
      "method": "ridge",
      "independent_field_count": 96,
      "model_seed_count": 3,
      "source_domain_count": 4,
      "classical_champion": "ridge",
      "mean_field_rel_l2": 0.5579373134920995,
      "mean_audit_reprojection_rel_l2": 0.6557429057235519,
      "mean_improvement_vs_classical_pct": 0.0,
      "median_improvement_vs_classical_pct": 0.0,
      "p10_improvement_vs_classical_pct": 0.0,
      "harm_rate_gt_1pct_vs_classical": 0.0,
      "improvement_ci95_cluster_low": 0.0,
      "improvement_ci95_cluster_high": 0.0
    },
    {
      "total_budget": 4,
      "method": "ridge_fno",
      "independent_field_count": 96,
      "model_seed_count": 3,
      "source_domain_count": 4,
      "classical_champion": "ridge",
      "mean_field_rel_l2": 0.46130451415148044,
      "mean_audit_reprojection_rel_l2": 0.5598067184910178,
      "mean_improvement_vs_classical_pct": 21.53849836804634,
      "median_improvement_vs_classical_pct": 9.688070298173187,
      "p10_improvement_vs_classical_pct": 4.274020189304392,
      "harm_rate_gt_1pct_vs_classical": 0.0,
      "improvement_ci95_cluster_low": 19.11448779883144,
      "improvement_ci95_cluster_high": 23.97390068272114
    },
    {
      "total_budget": 4,
      "method": "ridge_unet",
      "independent_field_count": 96,
      "model_seed_count": 3,
      "source_domain_count": 4,
      "classical_champion": "ridge",
      "mean_field_rel_l2": 0.4770732680335641,
      "mean_audit_reprojection_rel_l2": 0.5753311769157234,
      "mean_improvement_vs_classical_pct": 18.555026207570698,
      "median_improvement_vs_classical_pct": 6.58266334379334,
      "p10_improvement_vs_classical_pct": 1.6549333968391202,
      "harm_rate_gt_1pct_vs_classical": 0.0,
      "improvement_ci95_cluster_low": 16.129632523201348,
      "improvement_ci95_cluster_high": 20.936640163065665
    },
    {
      "total_budget": 4,
      "method": "unet",
      "independent_field_count": 96,
      "model_seed_count": 3,
      "source_domain_count": 4,
      "classical_champion": "ridge",
      "mean_field_rel_l2": 0.5809967102896836,
      "mean_audit_reprojection_rel_l2": 0.6565585490833554,
      "mean_improvement_vs_classical_pct": -0.6806530874871475,
      "median_improvement_vs_classical_pct": -11.382385002147972,
      "p10_improvement_vs_classical_pct": -16.981932057004098,
      "harm_rate_gt_1pct_vs_classical": 0.625,
      "improvement_ci95_cluster_low": -3.5238378773509513,
      "improvement_ci95_cluster_high": 2.1690365191984604
    },
    {
      "total_budget": 6,
      "method": "fno",
      "independent_field_count": 96,
      "model_seed_count": 3,
      "source_domain_count": 4,
      "classical_champion": "ridge",
      "mean_field_rel_l2": 0.5358200746381448,
      "mean_audit_reprojection_rel_l2": 0.6226569343254797,
      "mean_improvement_vs_classical_pct": -16.101086364114686,
      "median_improvement_vs_classical_pct": -29.370703417069482,
      "p10_improvement_vs_classical_pct": -36.09997953181483,
      "harm_rate_gt_1pct_vs_classical": 0.7604166666666666,
      "improvement_ci95_cluster_low": -20.624377428296416,
      "improvement_ci95_cluster_high": -11.66799272860172
    },
    {
      "total_budget": 6,
      "method": "physics_lift",
      "independent_field_count": 96,
      "model_seed_count": 3,
      "source_domain_count": 4,
      "classical_champion": "ridge",
      "mean_field_rel_l2": 0.6315130178506174,
      "mean_audit_reprojection_rel_l2": 0.7402202043061454,
      "mean_improvement_vs_classical_pct": -44.904487697598434,
      "median_improvement_vs_classical_pct": -38.711047135901396,
      "p10_improvement_vs_classical_pct": -75.49520254974088,
      "harm_rate_gt_1pct_vs_classical": 1.0,
      "improvement_ci95_cluster_low": -49.06675310995048,
      "improvement_ci95_cluster_high": -40.75273103681002
    },
    {
      "total_budget": 6,
      "method": "ridge",
      "independent_field_count": 96,
      "model_seed_count": 3,
      "source_domain_count": 4,
      "classical_champion": "ridge",
      "mean_field_rel_l2": 0.44497674501811463,
      "mean_audit_reprojection_rel_l2": 0.5098560221182803,
      "mean_improvement_vs_classical_pct": 0.0,
      "median_improvement_vs_classical_pct": 0.0,
      "p10_improvement_vs_classical_pct": 0.0,
      "harm_rate_gt_1pct_vs_classical": 0.0,
      "improvement_ci95_cluster_low": 0.0,
      "improvement_ci95_cluster_high": 0.0
    },
    {
      "total_budget": 6,
      "method": "ridge_fno",
      "independent_field_count": 96,
      "model_seed_count": 3,
      "source_domain_count": 4,
      "classical_champion": "ridge",
      "mean_field_rel_l2": 0.37609990598219967,
      "mean_audit_reprojection_rel_l2": 0.4524682180231644,
      "mean_improvement_vs_classical_pct": 19.67839140029911,
      "median_improvement_vs_classical_pct": 9.106334843236644,
      "p10_improvement_vs_classical_pct": 3.188330121247462,
      "harm_rate_gt_1pct_vs_classical": 0.0,
      "improvement_ci95_cluster_low": 17.224227101329618,
      "improvement_ci95_cluster_high": 22.0868408840626
    },
    {
      "total_budget": 6,
      "method": "ridge_unet",
      "independent_field_count": 96,
      "model_seed_count": 3,
      "source_domain_count": 4,
      "classical_champion": "ridge",
      "mean_field_rel_l2": 0.3920659820238749,
      "mean_audit_reprojection_rel_l2": 0.46485348702925766,
      "mean_improvement_vs_classical_pct": 16.098881570992027,
      "median_improvement_vs_classical_pct": 5.328516477466828,
      "p10_improvement_vs_classical_pct": -0.907972511678861,
      "harm_rate_gt_1pct_vs_classical": 0.08333333333333333,
      "improvement_ci95_cluster_low": 13.532208757863993,
      "improvement_ci95_cluster_high": 18.635473514555304
    },
    {
      "total_budget": 6,
      "method": "unet",
      "independent_field_count": 96,
      "model_seed_count": 3,
      "source_domain_count": 4,
      "classical_champion": "ridge",
      "mean_field_rel_l2": 0.5449325683423214,
      "mean_audit_reprojection_rel_l2": 0.6429796478607588,
      "mean_improvement_vs_classical_pct": -19.025491069125252,
      "median_improvement_vs_classical_pct": -30.517682827356754,
      "p10_improvement_vs_classical_pct": -37.681916122037485,
      "harm_rate_gt_1pct_vs_classical": 0.7708333333333333,
      "improvement_ci95_cluster_low": -23.290945149744562,
      "improvement_ci95_cluster_high": -14.686580153943126
    },
    {
      "total_budget": 8,
      "method": "fno",
      "independent_field_count": 96,
      "model_seed_count": 3,
      "source_domain_count": 4,
      "classical_champion": "ridge",
      "mean_field_rel_l2": 0.5055339916402266,
      "mean_audit_reprojection_rel_l2": 0.6324765042453591,
      "mean_improvement_vs_classical_pct": -21.529296576362103,
      "median_improvement_vs_classical_pct": -41.729779168174645,
      "p10_improvement_vs_classical_pct": -52.19923594498194,
      "harm_rate_gt_1pct_vs_classical": 0.7604166666666666,
      "improvement_ci95_cluster_low": -26.525442898379726,
      "improvement_ci95_cluster_high": -16.517728622216165
    },
    {
      "total_budget": 8,
      "method": "physics_lift",
      "independent_field_count": 96,
      "model_seed_count": 3,
      "source_domain_count": 4,
      "classical_champion": "ridge",
      "mean_field_rel_l2": 0.6156176465253035,
      "mean_audit_reprojection_rel_l2": 0.7801912060628334,
      "mean_improvement_vs_classical_pct": -54.960764246240814,
      "median_improvement_vs_classical_pct": -56.746524087479294,
      "p10_improvement_vs_classical_pct": -80.70371636060841,
      "harm_rate_gt_1pct_vs_classical": 0.9791666666666667,
      "improvement_ci95_cluster_low": -59.390643605523714,
      "improvement_ci95_cluster_high": -50.48013789202443
    },
    {
      "total_budget": 8,
      "method": "ridge",
      "independent_field_count": 96,
      "model_seed_count": 3,
      "source_domain_count": 4,
      "classical_champion": "ridge",
      "mean_field_rel_l2": 0.39950583937267464,
      "mean_audit_reprojection_rel_l2": 0.4929283346670369,
      "mean_improvement_vs_classical_pct": 0.0,
      "median_improvement_vs_classical_pct": 0.0,
      "p10_improvement_vs_classical_pct": 0.0,
      "harm_rate_gt_1pct_vs_classical": 0.0,
      "improvement_ci95_cluster_low": 0.0,
      "improvement_ci95_cluster_high": 0.0
    },
    {
      "total_budget": 8,
      "method": "ridge_fno",
      "independent_field_count": 96,
      "model_seed_count": 3,
      "source_domain_count": 4,
      "classical_champion": "ridge",
      "mean_field_rel_l2": 0.3438541241404083,
      "mean_audit_reprojection_rel_l2": 0.4435757135506719,
      "mean_improvement_vs_classical_pct": 16.909212524801557,
      "median_improvement_vs_classical_pct": 7.624022011836815,
      "p10_improvement_vs_classical_pct": 0.6907402476063137,
      "harm_rate_gt_1pct_vs_classical": 0.041666666666666664,
      "improvement_ci95_cluster_low": 14.609924237480694,
      "improvement_ci95_cluster_high": 19.21070074214928
    },
    {
      "total_budget": 8,
      "method": "ridge_unet",
      "independent_field_count": 96,
      "model_seed_count": 3,
      "source_domain_count": 4,
      "classical_champion": "ridge",
      "mean_field_rel_l2": 0.35446729397194254,
      "mean_audit_reprojection_rel_l2": 0.44872125010523534,
      "mean_improvement_vs_classical_pct": 14.394538501413649,
      "median_improvement_vs_classical_pct": 4.445790656905332,
      "p10_improvement_vs_classical_pct": -2.357052379944013,
      "harm_rate_gt_1pct_vs_classical": 0.17708333333333331,
      "improvement_ci95_cluster_low": 11.94098855190486,
      "improvement_ci95_cluster_high": 16.741286208649274
    },
    {
      "total_budget": 8,
      "method": "unet",
      "independent_field_count": 96,
      "model_seed_count": 3,
      "source_domain_count": 4,
      "classical_champion": "ridge",
      "mean_field_rel_l2": 0.5071921598994069,
      "mean_audit_reprojection_rel_l2": 0.6316469566793077,
      "mean_improvement_vs_classical_pct": -21.430152189915354,
      "median_improvement_vs_classical_pct": -43.604123587551804,
      "p10_improvement_vs_classical_pct": -53.54536921392046,
      "harm_rate_gt_1pct_vs_classical": 0.7395833333333334,
      "improvement_ci95_cluster_low": -26.21342474530882,
      "improvement_ci95_cluster_high": -16.648571473858667
    }
  ],
  "domains": [
    {
      "total_budget": 4,
      "method": "fno",
      "source_split": "test_family_ood",
      "independent_field_count": 24,
      "mean_field_rel_l2": 0.7893277795778381,
      "mean_audit_reprojection_rel_l2": 0.8001767256193691,
      "mean_improvement_vs_classical_pct": -14.159217063162094
    },
    {
      "total_budget": 4,
      "method": "fno",
      "source_split": "test_iid",
      "independent_field_count": 24,
      "mean_field_rel_l2": 0.37742639105353093,
      "mean_audit_reprojection_rel_l2": 0.4536202446454101,
      "mean_improvement_vs_classical_pct": 9.842290946981969
    },
    {
      "total_budget": 4,
      "method": "fno",
      "source_split": "test_joint_ood",
      "independent_field_count": 24,
      "mean_field_rel_l2": 0.799259321557151,
      "mean_audit_reprojection_rel_l2": 0.8269885066482757,
      "mean_improvement_vs_classical_pct": -13.626785834248345
    },
    {
      "total_budget": 4,
      "method": "fno",
      "source_split": "test_noise_ood",
      "independent_field_count": 24,
      "mean_field_rel_l2": 0.379592367551393,
      "mean_audit_reprojection_rel_l2": 0.45331509825256133,
      "mean_improvement_vs_classical_pct": 9.312106259422851
    },
    {
      "total_budget": 4,
      "method": "physics_lift",
      "source_split": "test_family_ood",
      "independent_field_count": 24,
      "mean_field_rel_l2": 0.8550514504313469,
      "mean_audit_reprojection_rel_l2": 0.9009836291273435,
      "mean_improvement_vs_classical_pct": -23.854045616743935
    },
    {
      "total_budget": 4,
      "method": "physics_lift",
      "source_split": "test_iid",
      "independent_field_count": 24,
      "mean_field_rel_l2": 0.6270875086386999,
      "mean_audit_reprojection_rel_l2": 0.6170826889574528,
      "mean_improvement_vs_classical_pct": -51.16714382491775
    },
    {
      "total_budget": 4,
      "method": "physics_lift",
      "source_split": "test_joint_ood",
      "independent_field_count": 24,
      "mean_field_rel_l2": 0.8614806408683459,
      "mean_audit_reprojection_rel_l2": 0.8948816905419031,
      "mean_improvement_vs_classical_pct": -22.60396453211978
    },
    {
      "total_budget": 4,
      "method": "physics_lift",
      "source_split": "test_noise_ood",
      "independent_field_count": 24,
      "mean_field_rel_l2": 0.640573705236117,
      "mean_audit_reprojection_rel_l2": 0.6550974075992902,
      "mean_improvement_vs_classical_pct": -54.81677379062395
    },
    {
      "total_budget": 4,
      "method": "ridge",
      "source_split": "test_family_ood",
      "independent_field_count": 24,
      "mean_field_rel_l2": 0.6911488845944405,
      "mean_audit_reprojection_rel_l2": 0.7872540528575579,
      "mean_improvement_vs_classical_pct": 0.0
    },
    {
      "total_budget": 4,
      "method": "ridge",
      "source_split": "test_iid",
      "independent_field_count": 24,
      "mean_field_rel_l2": 0.41955478861927986,
      "mean_audit_reprojection_rel_l2": 0.5036681021253268,
      "mean_improvement_vs_classical_pct": 0.0
    },
    {
      "total_budget": 4,
      "method": "ridge",
      "source_split": "test_joint_ood",
      "independent_field_count": 24,
      "mean_field_rel_l2": 0.7031535704930624,
      "mean_audit_reprojection_rel_l2": 0.8059155493974686,
      "mean_improvement_vs_classical_pct": 0.0
    },
    {
      "total_budget": 4,
      "method": "ridge",
      "source_split": "test_noise_ood",
      "independent_field_count": 24,
      "mean_field_rel_l2": 0.4178920102616151,
      "mean_audit_reprojection_rel_l2": 0.5261339185138544,
      "mean_improvement_vs_classical_pct": 0.0
    },
    {
      "total_budget": 4,
      "method": "ridge_fno",
      "source_split": "test_family_ood",
      "independent_field_count": 24,
      "mean_field_rel_l2": 0.6506374080975851,
      "mean_audit_reprojection_rel_l2": 0.7415542859170171,
      "mean_improvement_vs_classical_pct": 5.929558810938912
    },
    {
      "total_budget": 4,
      "method": "ridge_fno",
      "source_split": "test_iid",
      "independent_field_count": 24,
      "mean_field_rel_l2": 0.2598034559438626,
      "mean_audit_reprojection_rel_l2": 0.3465954475104809,
      "mean_improvement_vs_classical_pct": 38.942625645650864
    },
    {
      "total_budget": 4,
      "method": "ridge_fno",
      "source_split": "test_joint_ood",
      "independent_field_count": 24,
      "mean_field_rel_l2": 0.6626515338818232,
      "mean_audit_reprojection_rel_l2": 0.7663014175163374,
      "mean_improvement_vs_classical_pct": 5.806331463552428
    },
    {
      "total_budget": 4,
      "method": "ridge_fno",
      "source_split": "test_noise_ood",
      "independent_field_count": 24,
      "mean_field_rel_l2": 0.272125658682651,
      "mean_audit_reprojection_rel_l2": 0.3847757230202357,
      "mean_improvement_vs_classical_pct": 35.47547755204316
    },
    {
      "total_budget": 4,
      "method": "ridge_unet",
      "source_split": "test_family_ood",
      "independent_field_count": 24,
      "mean_field_rel_l2": 0.6680145147773954,
      "mean_audit_reprojection_rel_l2": 0.7525489909781351,
      "mean_improvement_vs_classical_pct": 3.403084868154045
    },
    {
      "total_budget": 4,
      "method": "ridge_unet",
      "source_split": "test_iid",
      "independent_field_count": 24,
      "mean_field_rel_l2": 0.27737660250729984,
      "mean_audit_reprojection_rel_l2": 0.3713929000207119,
      "mean_improvement_vs_classical_pct": 34.74909155016926
    },
    {
      "total_budget": 4,
      "method": "ridge_unet",
      "source_split": "test_joint_ood",
      "independent_field_count": 24,
      "mean_field_rel_l2": 0.6775885000824928,
      "mean_audit_reprojection_rel_l2": 0.7733542968829473,
      "mean_improvement_vs_classical_pct": 3.6728304868931425
    },
    {
      "total_budget": 4,
      "method": "ridge_unet",
      "source_split": "test_noise_ood",
      "independent_field_count": 24,
      "mean_field_rel_l2": 0.2853134547670682,
      "mean_audit_reprojection_rel_l2": 0.4040285197810995,
      "mean_improvement_vs_classical_pct": 32.39509792506635
    },
    {
      "total_budget": 4,
      "method": "unet",
      "source_split": "test_family_ood",
      "independent_field_count": 24,
      "mean_field_rel_l2": 0.788886326054732,
      "mean_audit_reprojection_rel_l2": 0.8391565937134956,
      "mean_improvement_vs_classical_pct": -14.112414042884865
    },
    {
      "total_budget": 4,
      "method": "unet",
      "source_split": "test_iid",
      "independent_field_count": 24,
      "mean_field_rel_l2": 0.36168112481633824,
      "mean_audit_reprojection_rel_l2": 0.45712675423257876,
      "mean_improvement_vs_classical_pct": 13.980186894564454
    },
    {
      "total_budget": 4,
      "method": "unet",
      "source_split": "test_joint_ood",
      "independent_field_count": 24,
      "mean_field_rel_l2": 0.8027446568012238,
      "mean_audit_reprojection_rel_l2": 0.8549844067957667,
      "mean_improvement_vs_classical_pct": -14.137426628394858
    },
    {
      "total_budget": 4,
      "method": "unet",
      "source_split": "test_noise_ood",
      "independent_field_count": 24,
      "mean_field_rel_l2": 0.3706747334864404,
      "mean_audit_reprojection_rel_l2": 0.4749664415915807,
      "mean_improvement_vs_classical_pct": 11.547041426766683
    },
    {
      "total_budget": 6,
      "method": "fno",
      "source_split": "test_family_ood",
      "independent_field_count": 24,
      "mean_field_rel_l2": 0.7508515881167518,
      "mean_audit_reprojection_rel_l2": 0.8417008394996325,
      "mean_improvement_vs_classical_pct": -32.24639543607473
    },
    {
      "total_budget": 6,
      "method": "fno",
      "source_split": "test_iid",
      "independent_field_count": 24,
      "mean_field_rel_l2": 0.3147699298957984,
      "mean_audit_reprojection_rel_l2": 0.39506384916603565,
      "mean_improvement_vs_classical_pct": 2.4627325253635775
    },
    {
      "total_budget": 6,
      "method": "fno",
      "source_split": "test_joint_ood",
      "independent_field_count": 24,
      "mean_field_rel_l2": 0.7537513747811317,
      "mean_audit_reprojection_rel_l2": 0.8313447245293194,
      "mean_improvement_vs_classical_pct": -31.789376749645598
    },
    {
      "total_budget": 6,
      "method": "fno",
      "source_split": "test_noise_ood",
      "independent_field_count": 24,
      "mean_field_rel_l2": 0.3239074057588975,
      "mean_audit_reprojection_rel_l2": 0.4225183241069317,
      "mean_improvement_vs_classical_pct": -2.83130579610199
    },
    {
      "total_budget": 6,
      "method": "physics_lift",
      "source_split": "test_family_ood",
      "independent_field_count": 24,
      "mean_field_rel_l2": 0.7842185472448667,
      "mean_audit_reprojection_rel_l2": 0.8933982277909914,
      "mean_improvement_vs_classical_pct": -38.283156146916475
    },
    {
      "total_budget": 6,
      "method": "physics_lift",
      "source_split": "test_iid",
      "independent_field_count": 24,
      "mean_field_rel_l2": 0.47425302118062973,
      "mean_audit_reprojection_rel_l2": 0.5768926590681076,
      "mean_improvement_vs_classical_pct": -49.26121802936019
    },
    {
      "total_budget": 6,
      "method": "physics_lift",
      "source_split": "test_joint_ood",
      "independent_field_count": 24,
      "mean_field_rel_l2": 0.7864816412329674,
      "mean_audit_reprojection_rel_l2": 0.8728508452574412,
      "mean_improvement_vs_classical_pct": -37.6382101257621
    },
    {
      "total_budget": 6,
      "method": "physics_lift",
      "source_split": "test_noise_ood",
      "independent_field_count": 24,
      "mean_field_rel_l2": 0.48109886174400646,
      "mean_audit_reprojection_rel_l2": 0.6177390851080418,
      "mean_improvement_vs_classical_pct": -54.435366488354994
    },
    {
      "total_budget": 6,
      "method": "ridge",
      "source_split": "test_family_ood",
      "independent_field_count": 24,
      "mean_field_rel_l2": 0.568182036280632,
      "mean_audit_reprojection_rel_l2": 0.6415963967641195,
      "mean_improvement_vs_classical_pct": 0.0
    },
    {
      "total_budget": 6,
      "method": "ridge",
      "source_split": "test_iid",
      "independent_field_count": 24,
      "mean_field_rel_l2": 0.3248057961463928,
      "mean_audit_reprojection_rel_l2": 0.38382988423109055,
      "mean_improvement_vs_classical_pct": 0.0
    },
    {
      "total_budget": 6,
      "method": "ridge",
      "source_split": "test_joint_ood",
      "independent_field_count": 24,
      "mean_field_rel_l2": 0.5720089102784792,
      "mean_audit_reprojection_rel_l2": 0.6423603271444639,
      "mean_improvement_vs_classical_pct": 0.0
    },
    {
      "total_budget": 6,
      "method": "ridge",
      "source_split": "test_noise_ood",
      "independent_field_count": 24,
      "mean_field_rel_l2": 0.3149102373669545,
      "mean_audit_reprojection_rel_l2": 0.37163748033344746,
      "mean_improvement_vs_classical_pct": 0.0
    },
    {
      "total_budget": 6,
      "method": "ridge_fno",
      "source_split": "test_family_ood",
      "independent_field_count": 24,
      "mean_field_rel_l2": 0.5363397598266602,
      "mean_audit_reprojection_rel_l2": 0.6070016432139608,
      "mean_improvement_vs_classical_pct": 5.743216947280902
    },
    {
      "total_budget": 6,
      "method": "ridge_fno",
      "source_split": "test_iid",
      "independent_field_count": 24,
      "mean_field_rel_l2": 0.21612166075242892,
      "mean_audit_reprojection_rel_l2": 0.30288602546271354,
      "mean_improvement_vs_classical_pct": 34.22314231522657
    },
    {
      "total_budget": 6,
      "method": "ridge_fno",
      "source_split": "test_joint_ood",
      "independent_field_count": 24,
      "mean_field_rel_l2": 0.5376718329886595,
      "mean_audit_reprojection_rel_l2": 0.6073786566654841,
      "mean_improvement_vs_classical_pct": 6.129664231522632
    },
    {
      "total_budget": 6,
      "method": "ridge_fno",
      "source_split": "test_noise_ood",
      "independent_field_count": 24,
      "mean_field_rel_l2": 0.21426637036104998,
      "mean_audit_reprojection_rel_l2": 0.2926065467504992,
      "mean_improvement_vs_classical_pct": 32.617542107166344
    },
    {
      "total_budget": 6,
      "method": "ridge_unet",
      "source_split": "test_family_ood",
      "independent_field_count": 24,
      "mean_field_rel_l2": 0.5570946869750818,
      "mean_audit_reprojection_rel_l2": 0.6217833074430624,
      "mean_improvement_vs_classical_pct": 2.0649168067002637
    },
    {
      "total_budget": 6,
      "method": "ridge_unet",
      "source_split": "test_iid",
      "independent_field_count": 24,
      "mean_field_rel_l2": 0.2291942039090726,
      "mean_audit_reprojection_rel_l2": 0.3141102436929941,
      "mean_improvement_vs_classical_pct": 30.237048886240498
    },
    {
      "total_budget": 6,
      "method": "ridge_unet",
      "source_split": "test_joint_ood",
      "independent_field_count": 24,
      "mean_field_rel_l2": 0.5573581688933903,
      "mean_audit_reprojection_rel_l2": 0.6210457078284687,
      "mean_improvement_vs_classical_pct": 2.67918695769874
    },
    {
      "total_budget": 6,
      "method": "ridge_unet",
      "source_split": "test_noise_ood",
      "independent_field_count": 24,
      "mean_field_rel_l2": 0.22461686831795505,
      "mean_audit_reprojection_rel_l2": 0.3024746891525057,
      "mean_improvement_vs_classical_pct": 29.414373633328626
    },
    {
      "total_budget": 6,
      "method": "unet",
      "source_split": "test_family_ood",
      "independent_field_count": 24,
      "mean_field_rel_l2": 0.7533704729543792,
      "mean_audit_reprojection_rel_l2": 0.8557923030522135,
      "mean_improvement_vs_classical_pct": -32.71217975856984
    },
    {
      "total_budget": 6,
      "method": "unet",
      "source_split": "test_iid",
      "independent_field_count": 24,
      "mean_field_rel_l2": 0.3298518814974361,
      "mean_audit_reprojection_rel_l2": 0.42676678403384155,
      "mean_improvement_vs_classical_pct": -2.7888104704198518
    },
    {
      "total_budget": 6,
      "method": "unet",
      "source_split": "test_joint_ood",
      "independent_field_count": 24,
      "mean_field_rel_l2": 0.7563282830847635,
      "mean_audit_reprojection_rel_l2": 0.8385397253765,
      "mean_improvement_vs_classical_pct": -32.25520692544347
    },
    {
      "total_budget": 6,
      "method": "unet",
      "source_split": "test_noise_ood",
      "independent_field_count": 24,
      "mean_field_rel_l2": 0.3401796358327071,
      "mean_audit_reprojection_rel_l2": 0.45081977898048026,
      "mean_improvement_vs_classical_pct": -8.345767122067844
    },
    {
      "total_budget": 8,
      "method": "fno",
      "source_split": "test_family_ood",
      "independent_field_count": 24,
      "mean_field_rel_l2": 0.710246575375398,
      "mean_audit_reprojection_rel_l2": 0.8373078836335077,
      "mean_improvement_vs_classical_pct": -48.35437187581613
    },
    {
      "total_budget": 8,
      "method": "fno",
      "source_split": "test_iid",
      "independent_field_count": 24,
      "mean_field_rel_l2": 0.29967022252579534,
      "mean_audit_reprojection_rel_l2": 0.4215175229021244,
      "mean_improvement_vs_classical_pct": 4.739501466128234
    },
    {
      "total_budget": 8,
      "method": "fno",
      "source_split": "test_joint_ood",
      "independent_field_count": 24,
      "mean_field_rel_l2": 0.711059125761191,
      "mean_audit_reprojection_rel_l2": 0.8357152177227868,
      "mean_improvement_vs_classical_pct": -46.35741749122254
    },
    {
      "total_budget": 8,
      "method": "fno",
      "source_split": "test_noise_ood",
      "independent_field_count": 24,
      "mean_field_rel_l2": 0.30116004289852244,
      "mean_audit_reprojection_rel_l2": 0.4353653927230173,
      "mean_improvement_vs_classical_pct": 3.8551015954620085
    },
    {
      "total_budget": 8,
      "method": "physics_lift",
      "source_split": "test_family_ood",
      "independent_field_count": 24,
      "mean_field_rel_l2": 0.7556460127234459,
      "mean_audit_reprojection_rel_l2": 0.8992633024851481,
      "mean_improvement_vs_classical_pct": -58.078571729626766
    },
    {
      "total_budget": 8,
      "method": "physics_lift",
      "source_split": "test_iid",
      "independent_field_count": 24,
      "mean_field_rel_l2": 0.47328825667500496,
      "mean_audit_reprojection_rel_l2": 0.6496412952740988,
      "mean_improvement_vs_classical_pct": -51.717591713061786
    },
    {
      "total_budget": 8,
      "method": "physics_lift",
      "source_split": "test_joint_ood",
      "independent_field_count": 24,
      "mean_field_rel_l2": 0.7552965953946114,
      "mean_audit_reprojection_rel_l2": 0.8873542149861654,
      "mean_improvement_vs_classical_pct": -55.63836527910187
    },
    {
      "total_budget": 8,
      "method": "physics_lift",
      "source_split": "test_noise_ood",
      "independent_field_count": 24,
      "mean_field_rel_l2": 0.4782397213081519,
      "mean_audit_reprojection_rel_l2": 0.6845060115059217,
      "mean_improvement_vs_classical_pct": -54.408528263172805
    },
    {
      "total_budget": 8,
      "method": "ridge",
      "source_split": "test_family_ood",
      "independent_field_count": 24,
      "mean_field_rel_l2": 0.4799775034189224,
      "mean_audit_reprojection_rel_l2": 0.6055696432789167,
      "mean_improvement_vs_classical_pct": 0.0
    },
    {
      "total_budget": 8,
      "method": "ridge",
      "source_split": "test_iid",
      "independent_field_count": 24,
      "mean_field_rel_l2": 0.3187745586037636,
      "mean_audit_reprojection_rel_l2": 0.37841592108209926,
      "mean_improvement_vs_classical_pct": 0.0
    },
    {
      "total_budget": 8,
      "method": "ridge",
      "source_split": "test_joint_ood",
      "independent_field_count": 24,
      "mean_field_rel_l2": 0.48643498743573826,
      "mean_audit_reprojection_rel_l2": 0.6159960950414339,
      "mean_improvement_vs_classical_pct": 0.0
    },
    {
      "total_budget": 8,
      "method": "ridge",
      "source_split": "test_noise_ood",
      "independent_field_count": 24,
      "mean_field_rel_l2": 0.31283630803227425,
      "mean_audit_reprojection_rel_l2": 0.3717316792656978,
      "mean_improvement_vs_classical_pct": 0.0
    },
    {
      "total_budget": 8,
      "method": "ridge_fno",
      "source_split": "test_family_ood",
      "independent_field_count": 24,
      "mean_field_rel_l2": 0.46148307000597316,
      "mean_audit_reprojection_rel_l2": 0.5809780429634782,
      "mean_improvement_vs_classical_pct": 4.075761259941578
    },
    {
      "total_budget": 8,
      "method": "ridge_fno",
      "source_split": "test_iid",
      "independent_field_count": 24,
      "mean_field_rel_l2": 0.21772903555797204,
      "mean_audit_reprojection_rel_l2": 0.299957406707108,
      "mean_improvement_vs_classical_pct": 32.219510222676206
    },
    {
      "total_budget": 8,
      "method": "ridge_fno",
      "source_split": "test_joint_ood",
      "independent_field_count": 24,
      "mean_field_rel_l2": 0.4669378896554311,
      "mean_audit_reprojection_rel_l2": 0.5918695992893642,
      "mean_improvement_vs_classical_pct": 4.214224516665875
    },
    {
      "total_budget": 8,
      "method": "ridge_fno",
      "source_split": "test_noise_ood",
      "independent_field_count": 24,
      "mean_field_rel_l2": 0.22926650134225687,
      "mean_audit_reprojection_rel_l2": 0.3014978052427371,
      "mean_improvement_vs_classical_pct": 27.12735409992258
    },
    {
      "total_budget": 8,
      "method": "ridge_unet",
      "source_split": "test_family_ood",
      "independent_field_count": 24,
      "mean_field_rel_l2": 0.4775410770542092,
      "mean_audit_reprojection_rel_l2": 0.5891378708183765,
      "mean_improvement_vs_classical_pct": 0.6957453806454788
    },
    {
      "total_budget": 8,
      "method": "ridge_unet",
      "source_split": "test_iid",
      "independent_field_count": 24,
      "mean_field_rel_l2": 0.22587985524700746,
      "mean_audit_reprojection_rel_l2": 0.3049209877434704,
      "mean_improvement_vs_classical_pct": 29.665507478511813
    },
    {
      "total_budget": 8,
      "method": "ridge_unet",
      "source_split": "test_joint_ood",
      "independent_field_count": 24,
      "mean_field_rel_l2": 0.48133912061651546,
      "mean_audit_reprojection_rel_l2": 0.5976632771392664,
      "mean_improvement_vs_classical_pct": 1.2401698035792348
    },
    {
      "total_budget": 8,
      "method": "ridge_unet",
      "source_split": "test_noise_ood",
      "independent_field_count": 24,
      "mean_field_rel_l2": 0.23310912297003797,
      "mean_audit_reprojection_rel_l2": 0.30316286471982795,
      "mean_improvement_vs_classical_pct": 25.97673134291807
    },
    {
      "total_budget": 8,
      "method": "unet",
      "source_split": "test_family_ood",
      "independent_field_count": 24,
      "mean_field_rel_l2": 0.7194527213772138,
      "mean_audit_reprojection_rel_l2": 0.8540126805504163,
      "mean_improvement_vs_classical_pct": -50.25298087878625
    },
    {
      "total_budget": 8,
      "method": "unet",
      "source_split": "test_iid",
      "independent_field_count": 24,
      "mean_field_rel_l2": 0.29549350775778294,
      "mean_audit_reprojection_rel_l2": 0.4076113783650928,
      "mean_improvement_vs_classical_pct": 6.479883014289896
    },
    {
      "total_budget": 8,
      "method": "unet",
      "source_split": "test_joint_ood",
      "independent_field_count": 24,
      "mean_field_rel_l2": 0.7196898907423019,
      "mean_audit_reprojection_rel_l2": 0.8448784359627299,
      "mean_improvement_vs_classical_pct": -48.09669874367822
    },
    {
      "total_budget": 8,
      "method": "unet",
      "source_split": "test_noise_ood",
      "independent_field_count": 24,
      "mean_field_rel_l2": 0.29413251972032917,
      "mean_audit_reprojection_rel_l2": 0.42008533183899194,
      "mean_improvement_vs_classical_pct": 6.149187848513161
    }
  ],
  "verdicts": [
    {
      "total_budget": 4,
      "method": "unet",
      "minimum_gain_pct": 5.0,
      "maximum_harm_rate_gt_1pct": 0.05,
      "mean_gain_pct": -0.6806530874871475,
      "ci95_low": -3.5238378773509513,
      "ci95_high": 2.1690365191984604,
      "p10_gain_pct": -16.981932057004098,
      "harm_rate_gt_1pct": 0.625,
      "development_gate_pass": false
    },
    {
      "total_budget": 4,
      "method": "fno",
      "minimum_gain_pct": 5.0,
      "maximum_harm_rate_gt_1pct": 0.05,
      "mean_gain_pct": -2.157901422751405,
      "ci95_low": -5.1166645223296765,
      "ci95_high": 0.8842379337704652,
      "p10_gain_pct": -17.98324734056034,
      "harm_rate_gt_1pct": 0.65625,
      "development_gate_pass": false
    },
    {
      "total_budget": 4,
      "method": "ridge_unet",
      "minimum_gain_pct": 5.0,
      "maximum_harm_rate_gt_1pct": 0.05,
      "mean_gain_pct": 18.555026207570698,
      "ci95_low": 16.129632523201348,
      "ci95_high": 20.936640163065665,
      "p10_gain_pct": 1.6549333968391202,
      "harm_rate_gt_1pct": 0.0,
      "development_gate_pass": true
    },
    {
      "total_budget": 4,
      "method": "ridge_fno",
      "minimum_gain_pct": 5.0,
      "maximum_harm_rate_gt_1pct": 0.05,
      "mean_gain_pct": 21.53849836804634,
      "ci95_low": 19.11448779883144,
      "ci95_high": 23.97390068272114,
      "p10_gain_pct": 4.274020189304392,
      "harm_rate_gt_1pct": 0.0,
      "development_gate_pass": true
    },
    {
      "total_budget": 6,
      "method": "unet",
      "minimum_gain_pct": 5.0,
      "maximum_harm_rate_gt_1pct": 0.05,
      "mean_gain_pct": -19.025491069125252,
      "ci95_low": -23.290945149744562,
      "ci95_high": -14.686580153943126,
      "p10_gain_pct": -37.681916122037485,
      "harm_rate_gt_1pct": 0.7708333333333333,
      "development_gate_pass": false
    },
    {
      "total_budget": 6,
      "method": "fno",
      "minimum_gain_pct": 5.0,
      "maximum_harm_rate_gt_1pct": 0.05,
      "mean_gain_pct": -16.101086364114686,
      "ci95_low": -20.624377428296416,
      "ci95_high": -11.66799272860172,
      "p10_gain_pct": -36.09997953181483,
      "harm_rate_gt_1pct": 0.7604166666666666,
      "development_gate_pass": false
    },
    {
      "total_budget": 6,
      "method": "ridge_unet",
      "minimum_gain_pct": 5.0,
      "maximum_harm_rate_gt_1pct": 0.05,
      "mean_gain_pct": 16.098881570992027,
      "ci95_low": 13.532208757863993,
      "ci95_high": 18.635473514555304,
      "p10_gain_pct": -0.907972511678861,
      "harm_rate_gt_1pct": 0.08333333333333333,
      "development_gate_pass": false
    },
    {
      "total_budget": 6,
      "method": "ridge_fno",
      "minimum_gain_pct": 5.0,
      "maximum_harm_rate_gt_1pct": 0.05,
      "mean_gain_pct": 19.67839140029911,
      "ci95_low": 17.224227101329618,
      "ci95_high": 22.0868408840626,
      "p10_gain_pct": 3.188330121247462,
      "harm_rate_gt_1pct": 0.0,
      "development_gate_pass": true
    },
    {
      "total_budget": 8,
      "method": "unet",
      "minimum_gain_pct": 5.0,
      "maximum_harm_rate_gt_1pct": 0.05,
      "mean_gain_pct": -21.430152189915354,
      "ci95_low": -26.21342474530882,
      "ci95_high": -16.648571473858667,
      "p10_gain_pct": -53.54536921392046,
      "harm_rate_gt_1pct": 0.7395833333333334,
      "development_gate_pass": false
    },
    {
      "total_budget": 8,
      "method": "fno",
      "minimum_gain_pct": 5.0,
      "maximum_harm_rate_gt_1pct": 0.05,
      "mean_gain_pct": -21.529296576362103,
      "ci95_low": -26.525442898379726,
      "ci95_high": -16.517728622216165,
      "p10_gain_pct": -52.19923594498194,
      "harm_rate_gt_1pct": 0.7604166666666666,
      "development_gate_pass": false
    },
    {
      "total_budget": 8,
      "method": "ridge_unet",
      "minimum_gain_pct": 5.0,
      "maximum_harm_rate_gt_1pct": 0.05,
      "mean_gain_pct": 14.394538501413649,
      "ci95_low": 11.94098855190486,
      "ci95_high": 16.741286208649274,
      "p10_gain_pct": -2.357052379944013,
      "harm_rate_gt_1pct": 0.17708333333333331,
      "development_gate_pass": false
    },
    {
      "total_budget": 8,
      "method": "ridge_fno",
      "minimum_gain_pct": 5.0,
      "maximum_harm_rate_gt_1pct": 0.05,
      "mean_gain_pct": 16.909212524801557,
      "ci95_low": 14.609924237480694,
      "ci95_high": 19.21070074214928,
      "p10_gain_pct": 0.6907402476063137,
      "harm_rate_gt_1pct": 0.041666666666666664,
      "development_gate_pass": true
    }
  ]
}
