{
  "experiment": "t16_v3k_e_projected_bb_gate_v1",
  "selection_split": "val",
  "selection_metric": "source_field_mean_rel_l2_after_layout_collapse",
  "selection_tie_break": "fewer_total_operator_calls_then_fewer_iterations_then_variant_order_then_smaller_upper_bound",
  "selected_projected_bb": {
    "fno_strict": {
      "selection_split": "val",
      "start": "fno",
      "bb_mode": "strict",
      "bb_variant": "bb1",
      "initial_step_fraction": 1.9,
      "normalized_step_min_bound": 0.05,
      "normalized_step_max_bound": 1.9,
      "normalized_step_observed_min": 1.9,
      "normalized_step_observed_max": 1.9,
      "iterations": 64,
      "operator_a_calls_per_sample": 64,
      "operator_at_calls_per_sample": 64,
      "independent_field_count": 40,
      "layout_rows": 160,
      "source_field_mean_rel_l2": 0.14708340000308337,
      "source_field_median_rel_l2": 0.09937622272141042,
      "bb1_step_fraction": 0.984375,
      "bb2_step_fraction": 0.0,
      "fallback_step_fraction": 0.0,
      "clipped_low_fraction": 0.0,
      "clipped_high_fraction": 0.984375,
      "observed_objective_transition_count": 10080,
      "observed_objective_increase_fraction": 0.0,
      "selection_uses_audit_or_reprojection": false,
      "public_method": "fno_pbb_strict"
    },
    "fno_wide": {
      "selection_split": "val",
      "start": "fno",
      "bb_mode": "wide",
      "bb_variant": "alternating",
      "initial_step_fraction": 1.9,
      "normalized_step_min_bound": 0.05,
      "normalized_step_max_bound": 10.0,
      "normalized_step_observed_min": 1.1095450457796967,
      "normalized_step_observed_max": 10.0,
      "iterations": 64,
      "operator_a_calls_per_sample": 64,
      "operator_at_calls_per_sample": 64,
      "independent_field_count": 40,
      "layout_rows": 160,
      "source_field_mean_rel_l2": 0.13864020260204887,
      "source_field_median_rel_l2": 0.104657711469931,
      "bb1_step_fraction": 0.5,
      "bb2_step_fraction": 0.484375,
      "fallback_step_fraction": 0.0,
      "clipped_low_fraction": 0.0,
      "clipped_high_fraction": 0.39228515625,
      "observed_objective_transition_count": 10080,
      "observed_objective_increase_fraction": 0.00029761904761904765,
      "selection_uses_audit_or_reprojection": false,
      "public_method": "fno_pbb_wide"
    },
    "ridge_strict": {
      "selection_split": "val",
      "start": "ridge",
      "bb_mode": "strict",
      "bb_variant": "bb1",
      "initial_step_fraction": 1.9,
      "normalized_step_min_bound": 0.05,
      "normalized_step_max_bound": 1.9,
      "normalized_step_observed_min": 1.9,
      "normalized_step_observed_max": 1.9,
      "iterations": 64,
      "operator_a_calls_per_sample": 64,
      "operator_at_calls_per_sample": 64,
      "independent_field_count": 40,
      "layout_rows": 160,
      "source_field_mean_rel_l2": 0.1475810916063065,
      "source_field_median_rel_l2": 0.09837797110578494,
      "bb1_step_fraction": 0.984375,
      "bb2_step_fraction": 0.0,
      "fallback_step_fraction": 0.0,
      "clipped_low_fraction": 0.0,
      "clipped_high_fraction": 0.984375,
      "observed_objective_transition_count": 10080,
      "observed_objective_increase_fraction": 0.0,
      "selection_uses_audit_or_reprojection": false,
      "public_method": "ridge_pbb_strict"
    },
    "ridge_wide": {
      "selection_split": "val",
      "start": "ridge",
      "bb_mode": "wide",
      "bb_variant": "alternating",
      "initial_step_fraction": 1.9,
      "normalized_step_min_bound": 0.05,
      "normalized_step_max_bound": 10.0,
      "normalized_step_observed_min": 1.0943944406407458,
      "normalized_step_observed_max": 10.0,
      "iterations": 64,
      "operator_a_calls_per_sample": 64,
      "operator_at_calls_per_sample": 64,
      "independent_field_count": 40,
      "layout_rows": 160,
      "source_field_mean_rel_l2": 0.1392179978415005,
      "source_field_median_rel_l2": 0.103667302141333,
      "bb1_step_fraction": 0.5,
      "bb2_step_fraction": 0.484375,
      "fallback_step_fraction": 0.0,
      "clipped_low_fraction": 0.0,
      "clipped_high_fraction": 0.37890625,
      "observed_objective_transition_count": 10080,
      "observed_objective_increase_fraction": 0.0001984126984126984,
      "selection_uses_audit_or_reprojection": false,
      "public_method": "ridge_pbb_wide"
    }
  },
  "validation_scores": {
    "feasible_fno": {
      "source_field_mean_rel_l2": 0.24773916385946562,
      "source_field_median_rel_l2": 0.22428181136807235,
      "independent_field_count": 40
    },
    "fno_geometry": {
      "source_field_mean_rel_l2": 0.14708340000308337,
      "source_field_median_rel_l2": 0.09937622272141042,
      "independent_field_count": 40
    },
    "fno_quadratic": {
      "source_field_mean_rel_l2": 0.14385507484329835,
      "source_field_median_rel_l2": 0.09971135663699593,
      "independent_field_count": 40
    },
    "fno_pbb_strict": {
      "source_field_mean_rel_l2": 0.14708340000308337,
      "source_field_median_rel_l2": 0.09937622272141042,
      "independent_field_count": 40
    },
    "fno_pbb_wide": {
      "source_field_mean_rel_l2": 0.13864020260204887,
      "source_field_median_rel_l2": 0.104657711469931,
      "independent_field_count": 40
    },
    "feasible_ridge": {
      "source_field_mean_rel_l2": 0.3783476236776185,
      "source_field_median_rel_l2": 0.3738331584598804,
      "independent_field_count": 40
    },
    "ridge_geometry": {
      "source_field_mean_rel_l2": 0.14758109160630647,
      "source_field_median_rel_l2": 0.09837797110578496,
      "independent_field_count": 40
    },
    "ridge_quadratic": {
      "source_field_mean_rel_l2": 0.14423093489819858,
      "source_field_median_rel_l2": 0.09876909114049856,
      "independent_field_count": 40
    },
    "ridge_pbb_strict": {
      "source_field_mean_rel_l2": 0.1475810916063065,
      "source_field_median_rel_l2": 0.09837797110578494,
      "independent_field_count": 40
    },
    "ridge_pbb_wide": {
      "source_field_mean_rel_l2": 0.1392179978415005,
      "source_field_median_rel_l2": 0.103667302141333,
      "independent_field_count": 40
    }
  },
  "validation_champion": "fno_pbb_wide",
  "validation_champion_label": "FNO + projected BB (wide)",
  "inherited_baseline_selection_commit_sha256": "61f789594c4a730ef045597e4a5e01cb8c366155ff10c1d975a5948960034c6a",
  "independent_selection_fields": 40,
  "selection_layout_rows": 160,
  "selection_sample_seed_sha256": "b85d25f36f83eccb727193bf2423464381351e928820dc4b9e118aaf55887260",
  "selection_geometry_sha256": "72cb6c4fce9be8f14aba144a2698709187c6954d7ef7da02934595bbce139310",
  "audit_camera_used_for_selection": false,
  "audit_or_reprojection_metrics_computed_by_selection_function": false,
  "test_field_or_metric_rows_present_at_commit": false,
  "strict_and_wide_selected_independently": true
}
