{
  "schema_version": "lgwo-a24-r2e0-invalid-attempt-1.0",
  "status": "INVALID_R2E0_V1_RUNTIME_NUMERICAL_TRANSFER_FAILURE_NO_RESULT",
  "experiment_id": "lgwo_a24_r2e0_cached_krylov_diagnosis_v1",
  "attempt_utc": "2026-07-20T20:12:32Z",
  "source_git_head": "3e73fdec7ca828c35ceb04983abe44361c61852c",
  "config_relative_path": "demo_t16_operator/configs/lgwo_a24_r2e0_cached_krylov_diagnosis_v1.json",
  "config_sha256": "PRIVATE_CACHE_MANIFEST_SHA256_REDACTED",
  "geometry_input_bundle_sha256": "PRIVATE_CACHE_MANIFEST_SHA256_REDACTED",
  "formal_run_exit_code": 1,
  "output_file_count_before_this_manifest": 0,
  "failure_stage": "first reused case, data-only reduced least-squares coefficient reconstruction",
  "exception_type": "ValueError",
  "exception_message": "basis and coefficients must be finite",
  "diagnosed_root_cause": "A combined MPS-float32 to CPU-float64 tensor transfer corrupted the reduced right-hand side. The repair must stage device transfer and dtype conversion separately and be frozen under a new config and output path.",
  "result_valid": false,
  "rerun_same_config_authorized": false,
  "algorithm_evidence_produced": false,
  "claim_boundary": {
    "algorithm_success": false,
    "reconstruction_success": false,
    "generalization_success": false,
    "paper_success": false,
    "breakthrough": false
  }
}
